PPP/__init__.py
PPP/pip_package_poster.py
pip_package_poster-0.0.1.dist-info/METADATA
pip_package_poster-0.0.1.dist-info/WHEEL
pip_package_poster-0.0.1.dist-info/top_level.txt
pip_package_poster-0.0.1.dist-info/RECORD
